my_package/__init__.py
my_package/core.py
my_package/utils/__init__.py
my_package/utils/helper.py
mypackage_edwardykh-0.1.0.dist-info/LICENSE
mypackage_edwardykh-0.1.0.dist-info/METADATA
mypackage_edwardykh-0.1.0.dist-info/WHEEL
mypackage_edwardykh-0.1.0.dist-info/entry_points.txt
mypackage_edwardykh-0.1.0.dist-info/top_level.txt
mypackage_edwardykh-0.1.0.dist-info/RECORD
