Metadata-Version: 2.1
Name: mypackage-edwardykh
Version: 0.1.0
Summary: 一个提供基础数学运算的Python包
Author-email: Your Name <your@email.com>
Classifier: Programming Language :: Python :: 3
Classifier: License :: OSI Approved :: MIT License
Classifier: Operating System :: OS Independent
Requires-Python: >=3.8
License-File: LICENSE
Provides-Extra: dev
Requires-Dist: pytest >=7.0 ; extra == 'dev'
Requires-Dist: pytest-cov >=4.0 ; extra == 'dev'
Requires-Dist: flake8 >=6.0 ; extra == 'dev'
Requires-Dist: twine >=4.0 ; extra == 'dev'
